{
    "one_fichier":{
        "regex":{
            "host": "(.+)1fichier.com/|(.+)alterupload.com/|(.+)cjoint.net/|(.+)desfichiers.com/|(.+)dfichiers.com/|(.+)megadl.fr/|(.+)mesfichiers.org/|(.+)piecejointe.net/|(.+)pjointe.com/|(.+)tenvoi.com/|(.+)dl4free.com/",
            "online": "float:none;margin:auto;font-weight:bold",
            "offline": "File not found !|<div style=\"line-height:1.5em;padding:30px;font-size:16px;font-weight:bold;text-align:center;margin:auto;color:#aa0000\">",
            "folder": "<td class=\"normal titre ohidden\" style=\"width:500px\">FileName</td>|<td class=\"normal titre ohidden\" style=\"width:500px\">Nom du fichier</td>"
        },
        "use_api": false,
        "uncheckable": false
    },
    "bayfiles":{
        "regex":{
            "host": "(.+)bayfiles.net/file/(.+)",
            "online": "<div id=\"download-header\">|<a class=\"highlighted-btn\" href=\"(.+)\">Premium Download</a>",
            "offline": "<p>The requested file could not be found.</p>",
            "folder": 0
        },
        "use_api": false,
        "uncheckable": false
    },
    "billionuploads":{
        "regex":{
            "host": "(.+)billionuploads.com/(.+)",
            "online": "<button class=\"btn\" type=\"submit\" id=\"btn_download\" name=\"submit_btn\" width=\"240\" height=\"60\">",
            "offline": "<div style=\"font-size: 55px;font-weight: bold;margin-top: 108px;margin-left: 45px;\">File Not found</div>",
            "folder": 0
        },
        "use_api": false,
        "uncheckable": false
    },
    "bitshare":{
        "regex":{
            "host": "(.+)bitshare.com/files/(.+)",
            "online": "<table  style=\"width:100%;\">",
            "offline": "<div class=\"quotbox2\">",
            "folder": 0
        },
        "use_api": false,
        "uncheckable": false
    },
    "datafilehost":{
        "regex":{
            "host": "(.+)datafilehost.com/(.+)",
            "online": "<form name=\"cbf\" style=\"width:250px;background:#eee;border:1px solid #ddd;margin:10px 8px 2px 0px;padding:3px;font-size:11px;",
            "offline": "deleted due to inactivity",
            "folder": 0
        },
        "use_api": false,
        "uncheckable": false
    },
    "depositfiles":{
        "regex":{
            "host": "(.+)depositfiles.com/files/(.+)|(.+)dfiles.eu/files/(.+)",
            "online": "<div class=\"file_size\">Taille du fichier: <b>(.+)</b></div>",
            "offline": "<div class=\"no_download_msg\" id=\"no_download_message\">",
            "folder": 0
        },
        "use_api": false,
        "uncheckable": false
    },
    "divxpress":{
        "regex":{
            "host": "(.+)divxpress.com/(.+)",
            "online": ";font-size:26px;font-weight:bold;color: #5e5e5e;\">",
            "offline": "<b>fichier non trouve </b>",
            "folder": 0
        },
        "use_api": false,
        "uncheckable": false
    },
    "filefactory":{
        "regex":{
            "host": "(.+)filefactory.com/file/(.+)",
            "online": "<input type=\"hidden\" name=\"redirect\" value=\"/file/(.+)\"/>",
            "offline": "<title>File Not Found(.+)</title>|<h2>Invalid Download Link</h2>",
            "folder": "<strong>This file is only available to Premium Members.</strong>"
        },
        "use_api": false,
        "uncheckable": false
    },
    "fileom":{
        "regex":{
            "host": "(.+)fileom.com/(.+)",
            "online": "<span class=\"size\">(.+)</span>",
            "offline": "<div class=\"page-title\">fichier non trouve </div>|<div class=\"page-title\">The file was removed by administrator</div>",
            "folder": 0
        },
        "use_api": false,
        "uncheckable": false
    },
    "fileparadox":{
        "regex":{
            "host": "(.+)fileparadox.in/(.+)",
            "online": "<font style=\"font-size:18px;\">",
            "offline": "<h1>fichier non trouve </h1>",
            "folder": 0
        },
        "use_api": false,
        "uncheckable": false
    },
    "filesupload":{
        "regex":{
            "host": "(.+)filesupload.org/(.+)",
            "online": "<th class=\"descr\">",
            "offline": "<li>File has been removed.</li>",
            "folder": 0
        },
        "use_api": false,
        "uncheckable": false
    },
    "freakshare":{
        "regex":{
            "host": "(.+)freakshare.com/files/(.+)",
            "online": "<b>Gratuit</b>",
            "offline": "<h1 style=\"text-align:left;\">erreur </h1>",
            "folder": 0
        },
        "use_api": false,
        "uncheckable": false
    },
    "free":{
        "regex":{
            "host": "(.+)dl.free.fr/(.+)",
            "online": "<td style=\"text-align: left; border: 1px solid #ffffff; padding: 2px\">Fichier:</td>",
            "offline": "Fichier inexistant.",
            "folder": 0
        },
        "use_api": false,
        "uncheckable": false
    },
    "gboxes":{
        "regex":{
            "host": "(.+)gboxes.com/(.+)",
            "online": "<input type=\"submit\" name=\"method_free\" value=\"",
            "offline": "<b>fichier non trouve </b>",
            "folder": 0
        },
        "use_api": false,
        "uncheckable": false
    },
    "gigasize":{
        "regex":{
            "host": "(.+)gigasize.com/get(.+)",
            "online": "<div class=\"fileInfo\">",
            "offline": "<h2 class=\"error\">(.+)</h2>",
            "folder": 0
        },
        "use_api": false,
        "uncheckable": false
    },
    "gigaup":{
        "regex":{
            "host": "(.+)gigaup.fr/\\?g=(.+)",
            "online": "<center><input type=\"submit\" name=\"dl_file\"(.+)</center>",
            "offline": "Supprimé car non téléchargé",
            "folder": 0
        },
        "use_api": false,
        "uncheckable": false
    },
    "groovesharing":{
        "regex":{
            "host": "(.+)groovesharing.com/(.+)",
            "online": "<h3 class=\"remove-margin\">(.+)</h3>",
            "offline": "<li>- Le lien du fichier est incorrect </li>",
            "folder": 0
        },
        "use_api": false,
        "uncheckable": false
    },
    "hugefiles":{
        "regex":{
            "host": "(.+)hugefiles.net/(.+)",
            "online": "<span style=\"font-size:16px; font-family:Arial, Helvetica, sans-serif; font-weight:normal; color:#5c5c5c;\">(.+)</span>",
            "offline": "margin-top:2px; margin-bottom:2px;\">File Not Found:</p>",
            "folder": 0
        },
        "use_api": false,
        "uncheckable": false
    },
    "hulkfile":{
        "regex":{
            "host": "(.+)hulkfile.eu/(.+)",
            "online": "<h2 style=\"font-weight:normal !important; margin-bottom:5px; font-family:Arial, Helvetica, sans-serif !important; font-size:17px;\">FILE NAME:</h2>",
            "offline": "<h3>File Not found</h3>",
            "folder": 0
        },
        "use_api": false,
        "uncheckable": false
    },
    "jumbofiles":{
        "regex":{
            "host": "(.+)jumbofiles.com/\\w{12}",
            "online": "(.+)CONTENT=\"Download file (.+)\">",
            "offline": "Not Found(.+)",
            "folder": 0
        },
        "use_api": false,
        "uncheckable": false
    },
    "junocloud":{
        "regex":{
            "host": "(.+)junocloud.me/(.+)",
            "online": "<p class=\"request_filesize\">(.+)</p>",
            "offline": "<h1>fichier non trouve </h1>",
            "folder": 0
        },
        "use_api": false,
        "uncheckable": false
    },
    "nowdownload":{
        "regex":{
            "host": "(.+)nowdownload.ch/dl/(.+)",
            "online": "<input type=\"button\" class=\"btn btn-success\" id=\"regular_download\" value=\"REGULAR DOWNLOAD\">",
            "offline": "<p class=\"alert alert-danger\">This file does not exist!</p>",
            "folder": 0
        },
        "use_api": false,
        "uncheckable": false
    },
    "partage_facile":{
        "regex":{
            "host": "(.+)partage-facile.com/(.+)|(.+)paf.im/(.+)",
            "online": "<td>(.+)</td>",
            "offline": "<h1>Envoyez vos fichiers maintenant</h1>",
            "folder": 0
        },
        "use_api": false,
        "uncheckable": false
    },
    "putlocker":{
        "regex":{
            "host": "(.+)putlocker.com/file/(.+)|(.+)firedrive.com/file/(.+)",
            "online": "<div class=\"external_title_left\">(.+)</div>",
            "offline": "This file might have been moved, replaced or deleted.</div>",
            "folder": 0
        },
        "use_api": false,
        "uncheckable": false
    },
    "rapidgator":{
        "regex":{
            "host": "(.+)rapidgator.net/file/(.+)|(.+)rg.to/file/(.+)",
            "online": "<p style=\"word-wrap: break-word;width: 490px;line-height: 19px;\">",
            "offline": "<h3>Fichier non trouvé</h3>|<span>Obtenez les avantages du compte Premium dès maintenant !</span>",
            "folder": 0
        },
        "use_api": false,
        "uncheckable": false
    },
    "rockfile":{
        "regex":{
            "host": "(.+)rockfile.eu/(.+)",
            "online": "<input type=\"submit\" name=\"method_free\" id=\"freeDownload\"",
            "offline": "<div style=\"width:700px;text-align:center; font-size:25pt;\" id=\"searching\"> <i class=\"fa fa-spinner fa-spin\"></i> Looking for File ... </div>",
            "folder":0
        },
        "use_api": false,
        "uncheckable": false
    },
    "share_online":{
        "regex":{
            "host": "(.+)share-online.biz/dl/(.+)",
            "online": "(.+)var file(.+)",
            "offline": "<div id=\"dl_failure\" class=\"ui-widget\">",
            "folder": 0
        },
        "use_api": false,
        "uncheckable": false
    },
    "solidfiles":{
        "regex":{
            "host": "(.+)solidfiles.com/(.+)",
            "online": "File size",
            "offline": "The file you are trying to download has been claimed by a copyright holder",
            "folder": 0
        },
        "use_api": false,
        "uncheckable": false
    },
    "turbobit":{
        "regex":{
            "host": "(.+)turbobit.net/(.+).html",
            "online": "<span class=\"file-title\" id=\"file-title\">(.+)</span>",
            "offline": "<h1>Searching file...Please wait...</h1>",
            "folder": 0
        },
        "use_api": false,
        "uncheckable": false
    },
    "toutbox":{
        "regex":{
            "host": "(.+)toutbox.fr/(.+)",
            "online": "<a href=\"(.+)\" class=\"redButtonCSS downloadAction\" title=\"Download\">",
            "offline": 0,
            "folder": "<div class=\"customColor\" style=\"font-size: 20px; padding: 20px 0 0 0; text-align: center\">"
        },
        "use_api": false,
        "uncheckable": false
    },
    "upafile":{
        "regex":{
            "host": "(.+)upafile.com/(.+)",
            "online": "<b>nom de fichier :</b>",
            "offline": "<b>fichier non trouve </b>",
            "folder": 0
        },
        "use_api": false,
        "uncheckable": false
    },
    "uptobox":{
        "regex":{
            "host": "(.+)uptobox.com/(.+)",
            "online": "<input type=\"hidden\" name=\"fname\" value=\"(.+)\">",
            "offline": "<span class=\"para_title\">Fichier introuvable </span><br /><br /><br />|<span class=\"para_title\">Berkas tidak ditemukan </span>|<span class=\"para_title\">File not found </span>",
            "folder": "<td style=\"width:250px\" class=\"tri\">"
        },
        "use_api": false,
        "uncheckable": false
    },
    "uploaded":{
        "regex":{
            "host": "(.+)uploaded.to/file/(.+)|(.+)ul.to/(.+)|(.+)uploaded.net/file/(.+)|(.+)uploaded.net/f/(.+)",
            "online": "(.+)<a href=\"(.+)\" id=\"filename\">(.+)</a>(.+)",
            "offline": "doesn't contain files",
            "folder": "<div class=\"center\" id=\"folderc\">"
        },
        "use_api": false,
        "uncheckable": false
    },
    "uploading":{
        "regex":{
            "host": "(.+)uploading.com/files/(.+)",
            "online": "<h1><i class=\"small_header_up_icon\"></i>(.+)",
            "offline": "<i class=\"file_error\"></i>",
            "folder": 0
        },
        "use_api": false,
        "uncheckable": false
    },
    "uploadable":{
        "regex":{
            "host": "(.+)uploadable.ch/file/(.+)",
            "online": "<span>Slow Speed Download</span>",
            "offline": "<h1>File not available</h1>|<h1>This file is no longer available.</h1>",
            "folder": 0
        },
        "use_api": false,
        "uncheckable": false
    },
    "vozupload":{
        "regex":{
            "host": "(.+)vozupload.com/(.+)",
            "online": "<font style=\"color:#114\">(.+)</font>",
            "offline": "<b>File Not Found</b>",
            "folder": 0
        },
        "use_api": false,
        "uncheckable": false
    },
    "youwatch":{
        "regex":{
            "host": "(.+)youwatch.org/(.+)",
            "online": "<span style=\"font-style:italic; color:#bbbbbb;\">",
            "offline": "<div style=\"width:500px;text-align:left;\">",
            "folder": 0
        },
        "use_api": false,
        "uncheckable": false
    },
    "zippyshare":{
        "regex":{
            "host": "(.+)zippyshare.com/v/(.+)/file.html",
            "online": "<div class=\"left\" style=\"width: 700px;\">",
            "offline": "(.+)File does not exist on this server</div>|File has expired and does not exist anymore on this server",
            "folder": 0
        },
        "use_api": false
    },
    "mega":{
        "regex":{
            "host": "mega.nz|mega.co.nz",
            "online": 0,
            "offline": 0,
            "folder": 0
        },
        "use_api": true
    },
    "multiup":{
        "regex":{
            "host": "multiup.org",
            "online": 0,
            "offline": 0,
            "folder": 0
        },
        "use_api": true
    },
    "revivelink":{
        "regex":{
            "host": "revivelink\.com",
            "online": 0,
            "offline": 0,
            "folder": 0
        },
        "use_api": true
    }
}